<?xml version="1.0" encoding="utf-8"?>
<LanguageData>
  <!--The following translations were generated by https://www.deepl.com/-->
  <!-- EN: cultivated soil -->
  <Cultivated_Soil.label>耕地</Cultivated_Soil.label>
  <!-- EN: Cultivated soil for where there is none so that crops may grow. -->
  <Cultivated_Soil.description>在没有土壤的地方开垦土壤，让庄稼生长。</Cultivated_Soil.description>
  <!-- EN: dirt -->
  <Cultivated_Soil.tools.dirt.label>污垢</Cultivated_Soil.tools.dirt.label>
  <!-- EN: fertilized irrigated soil -->
  <Fertilized_Irrigated_Soil.label>施肥灌溉土壤</Fertilized_Irrigated_Soil.label>
  <!-- EN: Fertilized and irrigated soil for faster growing crops. -->
  <Fertilized_Irrigated_Soil.description>施肥和灌溉土壤，使作物生长更快。</Fertilized_Irrigated_Soil.description>
  <Fertilized_Irrigated_Soil.tools.dirt.label>污垢</Fertilized_Irrigated_Soil.tools.dirt.label>
  <!-- EN: fertilized soil -->
  <Fertilized_Soil.label>肥沃的土壤</Fertilized_Soil.label>
  <!-- EN: Fertilized soil for faster growing crops. -->
  <Fertilized_Soil.description>施肥的土壤使作物生长更快。</Fertilized_Soil.description>
  <Fertilized_Soil.tools.dirt.label>污垢</Fertilized_Soil.tools.dirt.label>
</LanguageData>
